README.rst
setup.py
maximshumilo_tools.egg-info/PKG-INFO
maximshumilo_tools.egg-info/SOURCES.txt
maximshumilo_tools.egg-info/dependency_links.txt
maximshumilo_tools.egg-info/not-zip-safe
maximshumilo_tools.egg-info/requires.txt
maximshumilo_tools.egg-info/top_level.txt
ms_tools/__init__.py
ms_tools/avito_api.py
ms_tools/common.py
ms_tools/sbr_api.py
ms_tools/tg_event_messeger.py
ms_tools/flask/__init__.py
ms_tools/flask/api.py
ms_tools/flask/sessions.py
ms_tools/flask/test_case/__init__.py
ms_tools/flask/test_case/nosql.py