Metadata-Version: 1.2
Name: maximshumilo-tools
Version: 1.1.7
Summary: My tools for developing
Home-page: https://github.com/maximshumilo/tools
Author: Shumilo Maksim
Author-email: shumilo.mk@gmail.com
License: UNKNOWN
Platform: UNKNOWN
Classifier: Development Status :: 4 - Beta
Classifier: Intended Audience :: Developers
Classifier: License :: OSI Approved :: MIT License
Classifier: Programming Language :: Python :: 3.8
Requires-Python: >=3.8
